fin_stresstest/__init__.py
fin_stresstest/add_historical_simulation.py
fin_stresstest/core.py
fin_stresstest/models.py
fin_stresstest/utils.py
fin_stresstest/visualization.py
fin_stresstest-0.1.3.dist-info/METADATA
fin_stresstest-0.1.3.dist-info/WHEEL
fin_stresstest-0.1.3.dist-info/top_level.txt
fin_stresstest-0.1.3.dist-info/RECORD
