Metadata-Version: 2.1
Name: fin-stresstest
Version: 0.1.3
Summary: Herramienta para análisis de escenarios de estrés financiero
Home-page: https://github.com/LuisHCalderon/StressTest
Author: Luis Humberto Calderon Baldeón
Author-email: luis.calderon.b@uni.pe
Classifier: Programming Language :: Python :: 3
Classifier: License :: OSI Approved :: MIT License
Classifier: Operating System :: OS Independent
Classifier: Topic :: Office/Business :: Financial
Classifier: Topic :: Scientific/Engineering :: Mathematics
Requires-Python: >=3.7
Requires-Dist: numpy>=1.20.0
Requires-Dist: pandas>=1.3.0
Requires-Dist: scipy>=1.7.0
Requires-Dist: matplotlib>=3.4.0
Requires-Dist: seaborn>=0.11.0
Requires-Dist: statsmodels>=0.12.0
Requires-Dist: yfinance>=0.2.0
